README.md
setup.py
yamconv.py
common/__init__.py
common/ex.py
common/prepro.py
mlt/__init__.py
mlt/conv.py
mlt/csv.py
mlt/fasttext.py
mlt/formatter.py
mlt/mlt.py
mlt/sqlite.py
yamconv.egg-info/PKG-INFO
yamconv.egg-info/SOURCES.txt
yamconv.egg-info/dependency_links.txt
yamconv.egg-info/top_level.txt
yamconv.egg-info/zip-safe