Metadata-Version: 2.1
Name: yamconv
Version: 0.1.7
Summary: yamconv converts the file formats of machine learning datasets
Home-page: https://github.com/yam-ai/yamconv
Author: Thomas Lee
Author-email: thomaslee@yam.ai
License: UNKNOWN
Keywords: machine learning
Platform: UNKNOWN
Classifier: Development Status :: 3 - Alpha
Classifier: License :: OSI Approved :: Apache Software License
Classifier: Programming Language :: Python :: 3.6
Classifier: Topic :: Scientific/Engineering :: Artificial Intelligence
